multi_resource_limiter/rate_limiter.py
multi_resource_limiter/factories/__init__.py
multi_resource_limiter/factories/openai/__init__.py
multi_resource_limiter/factories/openai/openai_rate_limiter.py
multi_resource_limiter/factories/openai/token_counter.py
multi_resource_limiter/interfaces/__init__.py
multi_resource_limiter/interfaces/callbacks.py
multi_resource_limiter/interfaces/interfaces.py
multi_resource_limiter/interfaces/models.py
multi_resource_limiter/limiter_backends/__init__.py
multi_resource_limiter/limiter_backends/redis/__init__.py
multi_resource_limiter/limiter_backends/redis/_bucket.py
multi_resource_limiter/limiter_backends/redis/backend.py
multi_resource_limiter-0.1.1.dist-info/METADATA
multi_resource_limiter-0.1.1.dist-info/WHEEL
multi_resource_limiter-0.1.1.dist-info/top_level.txt
multi_resource_limiter-0.1.1.dist-info/RECORD
