Metadata-Version: 2.4
Name: multi-resource-limiter
Version: 0.1.1
Summary: Robust Asyncio Rate Limiter for Complex API Quotas (Tokens, Requests, etc.).
Requires-Python: >=3.10
Requires-Dist: redis>=5.2.1
